README.rst
setup.py
captcha_solver/__init__.py
captcha_solver/error.py
captcha_solver/network.py
captcha_solver/solver.py
captcha_solver.egg-info/PKG-INFO
captcha_solver.egg-info/SOURCES.txt
captcha_solver.egg-info/dependency_links.txt
captcha_solver.egg-info/requires.txt
captcha_solver.egg-info/top_level.txt
captcha_solver/backend/__init__.py
captcha_solver/backend/antigate.py
captcha_solver/backend/base.py
captcha_solver/backend/browser.py
captcha_solver/backend/gui.py
captcha_solver/backend/rucaptcha.py
captcha_solver/backend/twocaptcha.py
test/__init__.py
test/test_browser.py
test/test_gui.py
test/test_solver.py